invplot.py
InvPyplot-1.0.dist-info/LICENSE
InvPyplot-1.0.dist-info/METADATA
InvPyplot-1.0.dist-info/WHEEL
InvPyplot-1.0.dist-info/top_level.txt
InvPyplot-1.0.dist-info/RECORD
