Metadata-Version: 2.1
Name: InvPyplot
Version: 1.0
Summary: Python package enabling plotting of .inv files exported from Res2DInv in matplotlib
License: MIT License
Project-URL: Homepage, https://github.com/RJbalikian/InvPyplot
Keywords: Res2dInv,electrical,resistivity,geophysics,plot,inv
Classifier: Programming Language :: Python :: 3
Classifier: License :: OSI Approved :: MIT License
Classifier: Operating System :: OS Independent
Requires-Python: >=3.0
License-File: LICENSE
Requires-Dist: numpy
Requires-Dist: pandas
Requires-Dist: matplotlib
Requires-Dist: scipy
